ansys/tools/versioning/__init__.py
ansys/tools/versioning/exceptions.py
ansys/tools/versioning/utils.py
pyansys_tools_versioning-0.7.0.dist-info/licenses/LICENSE
pyansys_tools_versioning-0.7.0.dist-info/WHEEL
pyansys_tools_versioning-0.7.0.dist-info/METADATA
pyansys_tools_versioning-0.7.0.dist-info/RECORD
