Metadata-Version: 2.4
Name: pyansys-tools-versioning
Version: 0.7.0
Summary: PyAnsys Tools Versioning.
Author-email: "ANSYS, Inc." <pyansys.core@ansys.com>
Maintainer-email: "ANSYS, Inc." <pyansys.core@ansys.com>
Requires-Python: >=3.10,<4
Classifier: Development Status :: 4 - Beta
Classifier: Programming Language :: Python :: 3.10
Classifier: Programming Language :: Python :: 3.11
Classifier: Programming Language :: Python :: 3.12
Classifier: Programming Language :: Python :: 3.13
Classifier: License :: OSI Approved :: MIT License
Classifier: Operating System :: OS Independent
License-File: LICENSE
Requires-Dist: ansys-tools-common
Requires-Dist: ansys_sphinx_theme[autoapi]==1.6.3 ; extra == "doc"
Requires-Dist: numpydoc==1.9.0 ; extra == "doc"
Requires-Dist: Sphinx==8.2.3 ; extra == "doc"
Requires-Dist: Sphinx-copybutton==0.5.2 ; extra == "doc"
Requires-Dist: hypothesis==6.144.0 ; extra == "tests"
Requires-Dist: pytest==8.4.2 ; extra == "tests"
Requires-Dist: pytest-cov==6.3.0 ; extra == "tests"
Project-URL: Source, https://github.com/ansys/pyansys-tools-versioning
Provides-Extra: doc
Provides-Extra: tests
